iotedgeapplicationlinksdk/__init__.py
iotedgeapplicationlinksdk/client.py
iotedge_application_link_sdk-0.3.0.dist-info/METADATA
iotedge_application_link_sdk-0.3.0.dist-info/WHEEL
iotedge_application_link_sdk-0.3.0.dist-info/top_level.txt
iotedge_application_link_sdk-0.3.0.dist-info/RECORD
