Metadata-Version: 2.1
Name: iotedge-application-link-sdk
Version: 0.3.0
Summary: IoT Stack Edge application Link SDK
Home-page: https://pypi.org/project/iotedge_application_link_sdk/
Author: ucloud.cn
Author-email: ibu-bot@ucloud.cn
License: Apache 2 License
Platform: any
Requires-Dist: asyncio-nats-client (>=0.10.0)
Requires-Dist: cachetools (>=4.0.0)
